xaal/__init__.py
xaal/rest/__init__.py
xaal/rest/__main__.py
xaal/rest/app.py
xaal/rest/json.py
xaal/rest/static/device.html
xaal/rest/static/index.html
xaal/rest/static/jquery.min.js
xaal/rest/static/style.css
xaal_rest-0.3.3.dist-info/METADATA
xaal_rest-0.3.3.dist-info/WHEEL
xaal_rest-0.3.3.dist-info/top_level.txt
xaal_rest-0.3.3.dist-info/RECORD
