Metadata-Version: 2.4
Name: xaal.rest
Version: 0.3.3
Summary: xAAL devices REST API
Author-email: Jerome Kerdreux <Jerome.Kerdreux@imt-atlantique.fr>
License-Expression: GPL-3.0-or-later
Project-URL: Homepage, https://recherche.imt-atlantique.fr/xaal/
Project-URL: Documentation, https://gitlab.imt-atlantique.fr/xaal/code/python/-/blob/main/apps/rest/README.rst
Project-URL: Source, https://gitlab.imt-atlantique.fr/xaal/code/python/-/tree/main/apps/rest
Keywords: xaal,rest,json
Classifier: Programming Language :: Python
Classifier: Topic :: Home Automation
Requires-Dist: xaal.lib
Requires-Dist: xaal.monitor
Requires-Dist: bottle
Requires-Dist: gevent
Requires-Dist: gevent-websocket
Requires-Dist: python-rapidjson
